<?xml version="1.0" encoding="UTF-8" standalone="yes"?><imgdir name="01703124.img"><imgdir name="info"><canvas name="icon" width="34" height="34"><vector name="origin" x="1" y="33"/><string name="_hash" value="7ccf1fd39ea9f77c9ac678275168a04b1be1b37aca38881870446306e85a76a6"/></canvas><canvas name="iconRaw" width="34" height="34"><vector name="origin" x="1" y="33"/><string name="_hash" value="c230f33ff3bbfd49019d6f8e438e8e71d28a0809c372cbde0ce1630e0da6d86a"/></canvas><string name="islot" value="Wp"/><string name="vslot" value="Wp"/><int name="reqJob" value="0"/><int name="reqLevel" value="0"/><int name="reqSTR" value="0"/><int name="reqDEX" value="0"/><int name="reqINT" value="0"/><int name="reqLUK" value="0"/><int name="cash" value="1"/></imgdir><imgdir name="30"><imgdir name="walk1"><imgdir name="0"><canvas name="weapon" width="92" height="43"><vector name="origin" x="62" y="21"/><imgdir name="map"><vector name="navel" x="0" y="0"/></imgdir><string name="z" value="weapon"/><string name="_hash" value="aab1927ef6ced269d964cd1b540d201af5755aec823c2b19c6737993877d4b34"/></canvas></imgdir><imgdir name="1"><canvas name="weapon" width="87" height="44"><vector name="origin" x="65" y="20"/><imgdir name="map"><vector name="navel" x="0" y="0"/></imgdir><string name="z" value="weapon"/><string name="_hash" value="203b78a7e02c24249b74161ce07ae7f1a1352fa8a74820e3ae396dc8c6c3240e"/></canvas></imgdir><imgdir name="2"><canvas name="weapon" width="101" height="43"><vector name="origin" x="73" y="21"/><imgdir name="map"><vector name="navel" x="0" y="0"/></imgdir><string name="z" value="weapon"/><string name="_hash" value="5a34f3b3f5c1e6ca2e0d353ba6eae16f76469b1304b4d599cef78fe705b717fa"/></canvas></imgdir><imgdir name="3"><canvas name="weapon" width="109" height="39"><vector name="origin" x="72" y="22"/><imgdir name="map"><vector name="navel" x="0" y="0"/></imgdir><string name="z" value="weapon"/><string name="_hash" value="ef8c5c6a2326a3d303107f6822e0b6e29683c8eb0b74158a6b22ccb553ce18b9"/></canvas></imgdir></imgdir><imgdir name="walk2"><imgdir name="0"><canvas name="weapon" width="77" height="44"><vector name="origin" x="62" y="21"/><imgdir name="map"><vector name="navel" x="0" y="0"/></imgdir><string name="z" value="weaponOverArm"/><string name="_hash" value="10ea9fba3de81e24d2e5062f6323cddc87569404c24f75dc8ba746f64fb97f54"/></canvas></imgdir><imgdir name="1"><canvas name="weapon" width="77" height="43"><vector name="origin" x="65" y="20"/><imgdir name="map"><vector name="navel" x="0" y="0"/></imgdir><string name="z" value="weaponOverArm"/><string name="_hash" value="c507ca329aec26999e79db61dae551e28b818ee9aadf83ef37cfd771fb9380ff"/></canvas></imgdir><imgdir name="2"><canvas name="weapon" width="88" height="44"><vector name="origin" x="73" y="21"/><imgdir name="map"><vector name="navel" x="0" y="0"/></imgdir><string name="z" value="weaponOverArm"/><string name="_hash" value="68f7ed928290f211fd720af5d5ce5554f10df6c5cda144be2d1a90b21cba3680"/></canvas></imgdir><imgdir name="3"><canvas name="weapon" width="90" height="44"><vector name="origin" x="72" y="22"/><imgdir name="map"><vector name="navel" x="0" y="0"/></imgdir><string name="z" value="weaponOverArm"/><string name="_hash" value="ad6e9e2fe21bb1e6785ad89f3f49c1b2effb9729821a13d954eb0e8a7edaf0d9"/></canvas></imgdir></imgdir><imgdir name="stand1"><imgdir name="0"><canvas name="weapon" width="89" height="46"><vector name="origin" x="60" y="20"/><imgdir name="map"><vector name="navel" x="0" y="0"/></imgdir><string name="z" value="weapon"/><string name="_hash" value="dac258dab384df54583b62e2e120aa8cc7f4be2cf088d95a37bb0d07af69274a"/></canvas></imgdir><imgdir name="1"><canvas name="weapon" width="90" height="47"><vector name="origin" x="61" y="22"/><imgdir name="map"><vector name="navel" x="0" y="0"/></imgdir><string name="z" value="weapon"/><string name="_hash" value="3b0bafe65e69697b623bb0a55e151456d6c6f5730bdbfe468be1480a55bb67b8"/></canvas></imgdir><imgdir name="2"><canvas name="weapon" width="91" height="48"><vector name="origin" x="62" y="22"/><imgdir name="map"><vector name="navel" x="0" y="0"/></imgdir><string name="z" value="weapon"/><string name="_hash" value="c2606c70787d6c5c6d938b52200ef7c300b1d5fa76efc9f922df6331352662ad"/></canvas></imgdir></imgdir><imgdir name="stand2"><imgdir name="0"><canvas name="weapon" width="91" height="45"><vector name="origin" x="60" y="20"/><imgdir name="map"><vector name="navel" x="0" y="0"/></imgdir><string name="z" value="weaponOverArm"/><string name="_hash" value="c6fb63f536a856c6a1d0acfca6ddad82a1939eef6e136e87e2e88387d563687d"/></canvas></imgdir><imgdir name="1"><canvas name="weapon" width="90" height="46"><vector name="origin" x="61" y="22"/><imgdir name="map"><vector name="navel" x="0" y="0"/></imgdir><string name="z" value="weaponOverArm"/><string name="_hash" value="51455b61baf8e9de9beeaf84d506ceee104b2a1c5fe0031f8251cd7646beaeaf"/></canvas></imgdir><imgdir name="2"><canvas name="weapon" width="89" height="47"><vector name="origin" x="62" y="22"/><imgdir name="map"><vector name="navel" x="0" y="0"/></imgdir><string name="z" value="weaponOverArm"/><string name="_hash" value="86d24d5417ae29826f447f5b5b9c7ac162ef535bcc8a07b5629ae01ca16a3380"/></canvas></imgdir></imgdir><imgdir name="alert"><imgdir name="0"><canvas name="weapon" width="87" height="41"><vector name="origin" x="73" y="23"/><imgdir name="map"><vector name="navel" x="0" y="0"/></imgdir><string name="z" value="weaponOverArm"/><string name="_hash" value="3ea16f6e8beabe517d161a50ae2130d9e384bf1c2b952ef3cfae0e100a4199c2"/></canvas></imgdir><imgdir name="1"><canvas name="weapon" width="87" height="43"><vector name="origin" x="73" y="23"/><imgdir name="map"><vector name="navel" x="0" y="0"/></imgdir><string name="z" value="weaponOverArm"/><string name="_hash" value="a0a4a23af5294be25c5b08403317955c667ea76f70205d8c2042d44540751137"/></canvas></imgdir><imgdir name="2"><canvas name="weapon" width="87" height="45"><vector name="origin" x="73" y="23"/><imgdir name="map"><vector name="navel" x="0" y="0"/></imgdir><string name="z" value="weaponOverArm"/><string name="_hash" value="b1b294e01c3e9951340960b7beb48c592c95c09343df24a094ade92dd3006ea5"/></canvas></imgdir></imgdir><imgdir name="swingO1"><imgdir name="0"><canvas name="weapon" width="29" height="23"><vector name="origin" x="18" y="13"/><imgdir name="map"><vector name="navel" x="0" y="0"/></imgdir><string name="z" value="weaponBelowBody"/><string name="_hash" value="410e72588d034893ac6e3d449bb731929446318437ca380c62b0224d2641546f"/></canvas><canvas name="effect" width="30" height="30"><vector name="origin" x="-27" y="23"/><imgdir name="map"><vector name="navel" x="0" y="0"/></imgdir><string name="z" value="characterEnd"/><string name="_hash" value="b65029e7fd54d47cad0f12a783be7b9809eee756b22feed7d0df625a45c0d61b"/></canvas></imgdir><imgdir name="1"><canvas name="weapon" width="86" height="74"><vector name="origin" x="82" y="12"/><imgdir name="map"><vector name="navel" x="0" y="0"/></imgdir><string name="z" value="weaponBelowBody"/><string name="_hash" value="d9433673bb0c5e4312d425763f68dde70f6042ee659e9d83832d44b8e67f1da8"/></canvas><canvas name="effect" width="58" height="52"><vector name="origin" x="89" y="-17"/><imgdir name="map"><vector name="navel" x="0" y="0"/></imgdir><string name="z" value="characterEnd"/><string name="_hash" value="0de80df225327e26253a8e68d49fc117ead30dd3fb669cf0829f89852d55e998"/></canvas></imgdir><imgdir name="2"><canvas name="weapon" width="86" height="90"><vector name="origin" x="-5" y="85"/><imgdir name="map"><vector name="navel" x="0" y="0"/></imgdir><string name="z" value="weaponBelowBody"/><string name="_hash" value="680d375f3caca58ba95ae15f97b943493a52eb108dda098fa81e6c514d3dc103"/></canvas><canvas name="effect" width="211" height="154"><vector name="origin" x="97" y="113"/><imgdir name="map"><vector name="navel" x="0" y="0"/></imgdir><string name="z" value="characterEnd"/><string name="_hash" value="e5a4d9c83b0a9067bbcf7087517941de6a5b59473fa7a6549f3fcb6db1611417"/></canvas></imgdir></imgdir><imgdir name="swingO2"><imgdir name="0"><canvas name="weapon" width="23" height="35"><vector name="origin" x="29" y="27"/><imgdir name="map"><vector name="navel" x="0" y="0"/></imgdir><string name="z" value="weaponBelowBody"/><string name="_hash" value="796ee7a7194f53ea192814c0870fb3a2c053bc5bf8b1e6fdcaae4157eea17911"/></canvas><canvas name="effect" width="30" height="30"><vector name="origin" x="4" y="74"/><imgdir name="map"><vector name="navel" x="0" y="0"/></imgdir><string name="z" value="characterEnd"/><string name="_hash" value="de4117036dd993f62f56dd9a2dc322ebd9943f1905597e7724017e2f736a52d6"/></canvas></imgdir><imgdir name="1"><canvas name="weapon" width="74" height="56"><vector name="origin" x="83" y="43"/><imgdir name="map"><vector name="navel" x="0" y="0"/></imgdir><string name="z" value="weaponBelowBody"/><string name="_hash" value="38159edcf3f6bb2b3246ef2f2e5f7fa90be7f9d34ec9fb15fb188d7561ca2547"/></canvas><canvas name="effect" width="110" height="116"><vector name="origin" x="89" y="118"/><imgdir name="map"><vector name="navel" x="0" y="0"/></imgdir><string name="z" value="characterEnd"/><string name="_hash" value="58295d3fc852d2547e0a7cb279c6f8395f4019171ea2e116cd75d062e82d05e2"/></canvas></imgdir><imgdir name="2"><canvas name="weapon" width="132" height="93"><vector name="origin" x="90" y="16"/><imgdir name="map"><vector name="navel" x="0" y="0"/></imgdir><string name="z" value="weapon"/><string name="_hash" value="50de66085eb07f69845e40aba3a0dd0efb5e8b54e7c64e3ff1ce35ff27eb43dd"/></canvas><canvas name="effect" width="114" height="203"><vector name="origin" x="114" y="101"/><imgdir name="map"><vector name="navel" x="0" y="0"/></imgdir><string name="z" value="characterEnd"/><string name="_hash" value="08fc35b8a8b18128e601a43966a9f9419c1c11e5585a50a9133f6e2b4a9e9c1d"/></canvas></imgdir></imgdir><imgdir name="swingO3"><imgdir name="0"><canvas name="weapon" width="27" height="34"><vector name="origin" x="-5" y="22"/><imgdir name="map"><vector name="navel" x="0" y="0"/></imgdir><string name="z" value="weapon"/><string name="_hash" value="895481fca85df6a8d5259b3b8c371c8744b05ffb0aa39d5a6008426a2a2bd1bd"/></canvas><canvas name="effect" width="30" height="30"><vector name="origin" x="-45" y="65"/><imgdir name="map"><vector name="navel" x="0" y="0"/></imgdir><string name="z" value="characterEnd"/><string name="_hash" value="67f20cca4a935ab5aa64a4e0ba87f61495aaf95efdeea8378b6591f32bc5d1ba"/></canvas></imgdir><imgdir name="1"><canvas name="weapon" width="90" height="90"><vector name="origin" x="94" y="69"/><imgdir name="map"><vector name="navel" x="0" y="0"/></imgdir><string name="z" value="weaponBelowBody"/><string name="_hash" value="bb59c03dd9e8d5612213bc1b62b7aaa2622630806b9bd5233b59fafd228ec89d"/></canvas><canvas name="effect" width="135" height="86"><vector name="origin" x="100" y="115"/><imgdir name="map"><vector name="navel" x="0" y="0"/></imgdir><string name="z" value="characterEnd"/><string name="_hash" value="9e4505e4c9887a78f5d3038455a0d7b6f008c1a4eb05d374667d8a32661ed220"/></canvas></imgdir><imgdir name="2"><canvas name="weapon" width="91" height="95"><vector name="origin" x="16" y="13"/><imgdir name="map"><vector name="navel" x="0" y="0"/></imgdir><string name="z" value="weaponBelowBody"/><string name="_hash" value="44f204b9416cba02a9e45e34d87f39e1c18bf10f8e04c454f286236b374108e6"/></canvas><canvas name="effect" width="210" height="234"><vector name="origin" x="111" y="127"/><imgdir name="map"><vector name="navel" x="0" y="0"/></imgdir><string name="z" value="characterEnd"/><string name="_hash" value="0eb06c4a3c8073180119905ade98f3e2970c32ecca1938cf3a45944c096b2847"/></canvas></imgdir></imgdir><imgdir name="swingOF"><imgdir name="0"><canvas name="weapon" width="27" height="26"><vector name="origin" x="-6" y="20"/><imgdir name="map"><vector name="navel" x="0" y="0"/></imgdir><string name="z" value="weapon"/><string name="_hash" value="12973cfc6d23fda85f65b2e90954f754c9e6bd9e62a495cb1b5ad7bc7d80501e"/></canvas><canvas name="effect" width="30" height="30"><vector name="origin" x="-37" y="-11"/><imgdir name="map"><vector name="navel" x="0" y="0"/></imgdir><string name="z" value="characterEnd"/><string name="_hash" value="42284f3a9ab1913edb2bd4a597517a71bd95d2d1e2ce1ab769b2389aab2de98a"/></canvas></imgdir><imgdir name="1"><canvas name="weapon" width="39" height="106"><vector name="origin" x="24" y="105"/><imgdir name="map"><vector name="navel" x="0" y="0"/></imgdir><string name="z" value="backWeapon"/><string name="_hash" value="14143c1e83fea5bdc5121ad3283d7a011aea34f12c7621463101e85e8e6b93c1"/></canvas><canvas name="effect" width="1" height="1"><vector name="origin" x="31" y="115"/><imgdir name="map"><vector name="navel" x="0" y="0"/></imgdir><string name="z" value="characterEnd"/><string name="_inlink" value="30/swingO1/1/effect"/></canvas></imgdir><imgdir name="2"><canvas name="weapon" width="98" height="39"><vector name="origin" x="93" y="26"/><imgdir name="map"><vector name="navel" x="0" y="0"/></imgdir><string name="z" value="weaponBelowBody"/><string name="_hash" value="595bced20c83f101e639d4e18e7381f13e93caa6e76c2cea22fd23f19f1e187c"/></canvas><canvas name="effect" width="82" height="132"><vector name="origin" x="123" y="110"/><imgdir name="map"><vector name="navel" x="0" y="0"/></imgdir><string name="z" value="characterEnd"/><string name="_hash" value="9f21aa368db311b567adad35f25b0ef808aade5e3690a826bd4945bc73850654"/></canvas></imgdir><imgdir name="3"><canvas name="weapon" width="87" height="97"><vector name="origin" x="-1" y="23"/><imgdir name="map"><vector name="navel" x="0" y="0"/></imgdir><string name="z" value="weaponBelowBody"/><string name="_hash" value="d589da95e467a55fc6a3aa08e32f5ccd1aa9443aef1cb7711cf92c63aac50c88"/></canvas><canvas name="effect" width="213" height="189"><vector name="origin" x="102" y="90"/><imgdir name="map"><vector name="navel" x="0" y="0"/></imgdir><string name="z" value="characterEnd"/><string name="_hash" value="3484363cc63999726493355a283b7b9c0ac9e06786d21e31f03d2d843dc2e204"/></canvas></imgdir></imgdir><imgdir name="swingT1"><imgdir name="0"><canvas name="weapon" width="29" height="32"><vector name="origin" x="-3" y="37"/><imgdir name="map"><vector name="navel" x="0" y="0"/></imgdir><string name="z" value="weaponBelowArm"/><string name="_hash" value="2f867ddb8f57b6ddbea3b6cbd85e0c88d9ecb7e912e161458ca181171dd37ada"/></canvas><canvas name="effect" width="30" height="30"><vector name="origin" x="-53" y="58"/><imgdir name="map"><vector name="navel" x="0" y="0"/></imgdir><string name="z" value="characterEnd"/><string name="_hash" value="ea6e2efd26912510f91843b59b4313d410ec40faf748dd6b6c136070b04787aa"/></canvas></imgdir><imgdir name="1"><canvas name="weapon" width="39" height="115"><vector name="origin" x="30" y="111"/><imgdir name="map"><vector name="navel" x="0" y="0"/></imgdir><string name="z" value="weaponBelowArm"/><string name="_hash" value="47c303e1587264735f0cd92395050c2c4a0e37fe74125287072ab5fdb6d97c51"/></canvas><canvas name="effect" width="1" height="1"><vector name="origin" x="36" y="121"/><imgdir name="map"><vector name="navel" x="0" y="0"/></imgdir><string name="z" value="characterEnd"/><string name="_inlink" value="30/swingO1/1/effect"/></canvas></imgdir><imgdir name="2"><canvas name="weapon" width="82" height="79"><vector name="origin" x="80" y="-2"/><imgdir name="map"><vector name="navel" x="0" y="0"/></imgdir><string name="z" value="weaponBelowBody"/><string name="_hash" value="f3e04a60bb555dce50081e46f8483e2c67202274318aa6864b7eacbb58b523fe"/></canvas><canvas name="effect" width="120" height="219"><vector name="origin" x="110" y="114"/><imgdir name="map"><vector name="navel" x="0" y="0"/></imgdir><string name="z" value="characterEnd"/><string name="_hash" value="532ea11dee342ffdc31203e4e443c1cbc58020bb3eeeb0d43a13bc4e9a5b020d"/></canvas></imgdir></imgdir><imgdir name="swingT2"><imgdir name="0"><canvas name="weapon" width="26" height="37"><vector name="origin" x="13" y="35"/><imgdir name="map"><vector name="navel" x="0" y="0"/></imgdir><string name="z" value="weaponBelowBody"/><string name="_hash" value="7088462af1315035265f36feda5d6fc8f51e0676d721cff65d60d5132ba2fdb0"/></canvas><canvas name="effect" width="30" height="30"><vector name="origin" x="-12" y="76"/><imgdir name="map"><vector name="navel" x="0" y="0"/></imgdir><string name="z" value="characterEnd"/><string name="_hash" value="88f8f313c6c27204b4abd59ee9ad0586f0854c066fb507e23025e529da641b9b"/></canvas></imgdir><imgdir name="1"><canvas name="weapon" width="76" height="95"><vector name="origin" x="75" y="76"/><imgdir name="map"><vector name="navel" x="0" y="0"/></imgdir><string name="z" value="weaponBelowBody"/><string name="_hash" value="d18ec15883601f32049b7ca95dbdd0072e50a50659e535c9d0cf048c9934f94e"/></canvas><canvas name="effect" width="139" height="76"><vector name="origin" x="81" y="110"/><imgdir name="map"><vector name="navel" x="0" y="0"/></imgdir><string name="z" value="characterEnd"/><string name="_hash" value="043853f646af0d4ed685fe74c07340e87781474d2370efe2229239b8347a0fa9"/></canvas></imgdir><imgdir name="2"><canvas name="weapon" width="100" height="85"><vector name="origin" x="72" y="4"/><imgdir name="map"><vector name="navel" x="0" y="0"/></imgdir><string name="z" value="weaponOverBody"/><string name="_hash" value="1073f509bf626c183df5b679854d7aeaca5a67ad40d4bbca6235f054808fdcf0"/></canvas><canvas name="effect" width="153" height="214"><vector name="origin" x="107" y="109"/><imgdir name="map"><vector name="navel" x="0" y="0"/></imgdir><string name="z" value="characterEnd"/><string name="_hash" value="9e5395a1aee57b3545fefbaff934474ab8a32316777eea8d675086b1d7627177"/></canvas></imgdir></imgdir><imgdir name="swingT3"><imgdir name="0"><canvas name="weapon" width="29" height="26"><vector name="origin" x="8" y="4"/><imgdir name="map"><vector name="navel" x="0" y="0"/></imgdir><string name="z" value="weaponBelowBody"/><string name="_hash" value="ea48dd3774a2be3edf0c71b76dbe4ac12a6d7330b12f2cddd6eb025eff64fdc3"/></canvas><canvas name="effect" width="30" height="30"><vector name="origin" x="-44" y="12"/><imgdir name="map"><vector name="navel" x="0" y="0"/></imgdir><string name="z" value="characterEnd"/><string name="_hash" value="1a0e34fe5b9c19842e28317ec1dd0f01131b923e478deb33dd8a8678b6606907"/></canvas></imgdir><imgdir name="1"><canvas name="weapon" width="45" height="96"><vector name="origin" x="24" y="7"/><imgdir name="map"><vector name="navel" x="0" y="0"/></imgdir><string name="z" value="weaponBelowBody"/><string name="_hash" value="e866b1ef1d6ae0afa2c4585b3a9fc09c1695798d9c6f268bda155500a2bad672"/></canvas><canvas name="effect" width="114" height="108"><vector name="origin" x="30" y="11"/><imgdir name="map"><vector name="navel" x="0" y="0"/></imgdir><string name="z" value="characterEnd"/><string name="_hash" value="3c772902d485d22699340b6e1eef74f37d980ebe75826011af2687fe09ce96f1"/></canvas></imgdir><imgdir name="2"><canvas name="weapon" width="110" height="84"><vector name="origin" x="28" y="79"/><imgdir name="map"><vector name="navel" x="0" y="0"/></imgdir><string name="z" value="weaponBelowBody"/><string name="_hash" value="80b1046232e6a1b686e4561bb13141bac44f0a5d70eaa480b9ba0bf8f67e16b3"/></canvas><canvas name="effect" width="204" height="186"><vector name="origin" x="99" y="112"/><imgdir name="map"><vector name="navel" x="0" y="0"/></imgdir><string name="z" value="characterEnd"/><string name="_hash" value="7af511112aa46301a0e6f053a8f9a8e6767bb0d405a6ffbdc2943007528b8ed6"/></canvas></imgdir></imgdir><imgdir name="swingTF"><imgdir name="0"><canvas name="weapon" width="19" height="37"><vector name="origin" x="7" y="41"/><imgdir name="map"><vector name="navel" x="0" y="0"/></imgdir><string name="z" value="backWeapon"/><string name="_hash" value="3d92aead500e0a9075b815cc74513793cb7af895da977c9b7750768953ca3be2"/></canvas><canvas name="effect" width="30" height="30"><vector name="origin" x="12" y="99"/><imgdir name="map"><vector name="navel" x="0" y="0"/></imgdir><string name="z" value="characterEnd"/><string name="_hash" value="5c214da090ae57b93626b5095734240b97093678d760d6066d3bf800358bde17"/></canvas></imgdir><imgdir name="1"><canvas name="weapon" width="87" height="89"><vector name="origin" x="59" y="101"/><imgdir name="map"><vector name="navel" x="0" y="0"/></imgdir><string name="z" value="weaponBelowBody"/><string name="_hash" value="b1eedee9166b33e2c19177e4b94131420e189362e78437f178c658480b1e1421"/></canvas><canvas name="effect" width="1" height="1"><vector name="origin" x="65" y="111"/><imgdir name="map"><vector name="navel" x="0" y="0"/></imgdir><string name="z" value="characterEnd"/><string name="_inlink" value="30/swingO1/1/effect"/></canvas></imgdir><imgdir name="2"><canvas name="weapon" width="89" height="60"><vector name="origin" x="84" y="74"/><imgdir name="map"><vector name="navel" x="0" y="0"/></imgdir><string name="z" value="weaponBelowArm"/><string name="_hash" value="ef38d876701366d5c091f57e1fb598eceb1a9e50cd60b25c46375ff589fe671d"/></canvas><canvas name="effect" width="169" height="86"><vector name="origin" x="90" y="117"/><imgdir name="map"><vector name="navel" x="0" y="0"/></imgdir><string name="z" value="characterEnd"/><string name="_hash" value="5ec92e42dc31bbc8e3dbbd9cd1b0af4a67316be7f2f4cfc1bd6e7e4edf62dde3"/></canvas></imgdir><imgdir name="3"><canvas name="weapon" width="93" height="68"><vector name="origin" x="85" y="3"/><imgdir name="map"><vector name="navel" x="0" y="0"/></imgdir><string name="z" value="weaponBelowBody"/><string name="_hash" value="c8b02508f3c39a8ced9b116c8fceef85f34aa8b2afc394d3e7e82192ffd59851"/></canvas><canvas name="effect" width="156" height="206"><vector name="origin" x="108" y="118"/><imgdir name="map"><vector name="navel" x="0" y="0"/></imgdir><string name="z" value="characterEnd"/><string name="_hash" value="f5a7e7a750212ed8ddc7c5b38648ca877c98391bc65a04a62064b870dcb9e9bb"/></canvas></imgdir></imgdir><imgdir name="swingP1"><imgdir name="0"><canvas name="weapon" width="1" height="1"><vector name="origin" x="-1" y="39"/><imgdir name="map"><vector name="navel" x="0" y="0"/></imgdir><string name="z" value="weaponBelowArm"/><string name="_inlink" value="30/swingT1/0/weapon"/></canvas><canvas name="effect" width="1" height="1"><vector name="origin" x="-50" y="66"/><imgdir name="map"><vector name="navel" x="0" y="0"/></imgdir><string name="z" value="characterEnd"/><string name="_inlink" value="30/swingO1/0/effect"/></canvas></imgdir><imgdir name="1"><canvas name="weapon" width="39" height="104"><vector name="origin" x="32" y="102"/><imgdir name="map"><vector name="navel" x="0" y="0"/></imgdir><string name="z" value="weaponBelowArm"/><string name="_hash" value="aea8cc66dd6e84632d955b4ea6e2ca6ea6607ae02970ad4d626f60b97f2283b8"/></canvas><canvas name="effect" width="1" height="1"><vector name="origin" x="38" y="112"/><imgdir name="map"><vector name="navel" x="0" y="0"/></imgdir><string name="z" value="characterEnd"/><string name="_inlink" value="30/swingO1/1/effect"/></canvas></imgdir><imgdir name="2"><canvas name="weapon" width="83" height="79"><vector name="origin" x="82" y="-1"/><imgdir name="map"><vector name="navel" x="0" y="0"/></imgdir><string name="z" value="weaponBelowBody"/><string name="_hash" value="3e892de8288fd68e931dde1d5cec44e7ba5963157ded2e961dbc01acfdfaf841"/></canvas><canvas name="effect" width="1" height="1"><vector name="origin" x="112" y="115"/><imgdir name="map"><vector name="navel" x="0" y="0"/></imgdir><string name="z" value="characterEnd"/><string name="_inlink" value="30/swingT1/2/effect"/></canvas></imgdir></imgdir><imgdir name="swingP2"><imgdir name="0"><canvas name="weapon" width="1" height="1"><vector name="origin" x="28" y="26"/><imgdir name="map"><vector name="navel" x="0" y="0"/></imgdir><string name="z" value="weaponBelowBody"/><string name="_inlink" value="30/swingO2/0/weapon"/></canvas><canvas name="effect" width="1" height="1"><vector name="origin" x="11" y="74"/><imgdir name="map"><vector name="navel" x="0" y="0"/></imgdir><string name="z" value="characterEnd"/><string name="_inlink" value="30/swingO1/0/effect"/></canvas></imgdir><imgdir name="1"><canvas name="weapon" width="39" height="115"><vector name="origin" x="34" y="94"/><imgdir name="map"><vector name="navel" x="0" y="0"/></imgdir><string name="z" value="weaponBelowBody"/><string name="_hash" value="5265de6fe4dbfe0b5dbfcdcda66c2731c90c12516e179ed88101836dc97ae895"/></canvas><canvas name="effect" width="1" height="1"><vector name="origin" x="41" y="104"/><imgdir name="map"><vector name="navel" x="0" y="0"/></imgdir><string name="z" value="characterEnd"/><string name="_inlink" value="30/swingO1/1/effect"/></canvas></imgdir><imgdir name="2"><canvas name="weapon" width="97" height="85"><vector name="origin" x="73" y="4"/><imgdir name="map"><vector name="navel" x="0" y="0"/></imgdir><string name="z" value="weaponOverBody"/><string name="_hash" value="36c42bceb6ee8ce903fc8ee3f6a94eaae5d65f4d8784e7a89ff99c887cd2a527"/></canvas><canvas name="effect" width="1" height="1"><vector name="origin" x="109" y="109"/><imgdir name="map"><vector name="navel" x="0" y="0"/></imgdir><string name="z" value="characterEnd"/><string name="_inlink" value="30/swingT2/2/effect"/></canvas></imgdir></imgdir><imgdir name="swingPF"><imgdir name="0"><canvas name="weapon" width="29" height="26"><vector name="origin" x="-8" y="11"/><imgdir name="map"><vector name="navel" x="0" y="0"/></imgdir><string name="z" value="weapon"/><string name="_hash" value="36b09210f3d23875187397868d67b8468d904e589ef1a782ea4c05ebbcce8d1d"/></canvas><canvas name="effect" width="1" height="1"><vector name="origin" x="48" y="20"/><imgdir name="map"><vector name="navel" x="0" y="0"/></imgdir><string name="z" value="characterEnd"/><string name="_inlink" value="30/swingO1/0/effect"/></canvas></imgdir><imgdir name="1"><canvas name="weapon" width="58" height="73"><vector name="origin" x="-8" y="15"/><imgdir name="map"><vector name="navel" x="0" y="0"/></imgdir><string name="z" value="weapon"/><string name="_hash" value="e8b13d7d3b2213d0cd56fc8d980522a2723ac7cc785b6da31cb9c252705cdb05"/></canvas><canvas name="effect" width="1" height="1"><vector name="origin" x="-20" y="-13"/><imgdir name="map"><vector name="navel" x="0" y="0"/></imgdir><string name="z" value="characterEnd"/><string name="_inlink" value="30/swingO1/1/effect"/></canvas></imgdir><imgdir name="2"><canvas name="weapon" width="65" height="82"><vector name="origin" x="-1" y="88"/><imgdir name="map"><vector name="navel" x="0" y="0"/></imgdir><string name="z" value="weaponBelowArm"/><string name="_hash" value="2c32b357d1527f9d63853218b0f1bd0e4d262dd20fa8f221cb0f0e1e535f242a"/></canvas><canvas name="effect" width="86" height="127"><vector name="origin" x="-23" y="100"/><imgdir name="map"><vector name="navel" x="0" y="0"/></imgdir><string name="z" value="characterEnd"/><string name="_hash" value="14c35f87b339467a4e3956c7dfac546645883016a981f43e4c594f8f8c59a592"/></canvas></imgdir><imgdir name="3"><canvas name="weapon" width="104" height="72"><vector name="origin" x="100" y="7"/><imgdir name="map"><vector name="navel" x="0" y="0"/></imgdir><string name="z" value="weaponBelowBody"/><string name="_hash" value="8c5ad90e0ae7db5029555d440e51f9f1f43d88247d14c03a127cf3a2a220f0d3"/></canvas><canvas name="effect" width="1" height="1"><vector name="origin" x="123" y="117"/><imgdir name="map"><vector name="navel" x="0" y="0"/></imgdir><string name="z" value="characterEnd"/><string name="_inlink" value="30/swingTF/3/effect"/></canvas></imgdir></imgdir><imgdir name="stabO1"><imgdir name="0"><canvas name="weapon" width="1" height="1"><vector name="origin" x="-1" y="5"/><imgdir name="map"><vector name="navel" x="0" y="0"/></imgdir><string name="z" value="weapon"/><string name="_inlink" value="30/swingPF/0/weapon"/></canvas><canvas name="effect" width="175" height="30"><vector name="origin" x="61" y="21"/><imgdir name="map"><vector name="navel" x="0" y="0"/></imgdir><string name="z" value="characterEnd"/><string name="_hash" value="31d36348308ce39dcb53a55c36257d231e412e99dd74af917eae5f273cbbfa7c"/></canvas></imgdir><imgdir name="1"><canvas name="weapon" width="98" height="34"><vector name="origin" x="106" y="22"/><imgdir name="map"><vector name="navel" x="0" y="0"/></imgdir><string name="z" value="weapon"/><string name="_hash" value="6b557c5154cb3b1265cedd6623901edae269cfd22ffbc20b80e3ce6339b028c2"/></canvas><canvas name="effect" width="230" height="179"><vector name="origin" x="139" y="97"/><imgdir name="map"><vector name="navel" x="0" y="0"/></imgdir><string name="z" value="characterEnd"/><string name="_hash" value="1a1f5cb49c708e8f1a3ddd4be315579153054400d47cd19653f43ad5e7ed7417"/></canvas></imgdir></imgdir><imgdir name="stabO2"><imgdir name="0"><canvas name="weapon" width="1" height="1"><vector name="origin" x="3" y="18"/><imgdir name="map"><vector name="navel" x="0" y="0"/></imgdir><string name="z" value="weaponBelowArm"/><string name="_inlink" value="30/swingPF/0/weapon"/></canvas><canvas name="effect" width="1" height="1"><vector name="origin" x="58" y="10"/><imgdir name="map"><vector name="navel" x="0" y="0"/></imgdir><string name="z" value="characterEnd"/><string name="_inlink" value="30/swingO1/0/effect"/></canvas></imgdir><imgdir name="1"><canvas name="weapon" width="106" height="82"><vector name="origin" x="112" y="69"/><imgdir name="map"><vector name="navel" x="0" y="0"/></imgdir><string name="z" value="weaponBelowArm"/><string name="_hash" value="f3980f8f6024aa9d0c99c81452171dc673d9a9e3abfbe55056efa79553eaeeef"/></canvas><canvas name="effect" width="203" height="102"><vector name="origin" x="119" y="85"/><imgdir name="map"><vector name="navel" x="0" y="0"/></imgdir><string name="z" value="characterEnd"/><string name="_hash" value="1877327d26ec66d86f25fe2dd3b9dc5be443b73bcb268effb18e656e888f9995"/></canvas></imgdir></imgdir><imgdir name="stabOF"><imgdir name="0"><canvas name="weapon" width="1" height="1"><vector name="origin" x="5" y="8"/><imgdir name="map"><vector name="navel" x="0" y="0"/></imgdir><string name="z" value="weapon"/><string name="_inlink" value="30/swingPF/0/weapon"/></canvas><canvas name="effect" width="1" height="1"><vector name="origin" x="66" y="14"/><imgdir name="map"><vector name="navel" x="0" y="0"/></imgdir><string name="z" value="characterEnd"/><string name="_inlink" value="30/swingO1/0/effect"/></canvas></imgdir><imgdir name="1"><canvas name="weapon" width="122" height="53"><vector name="origin" x="96" y="35"/><imgdir name="map"><vector name="navel" x="0" y="0"/></imgdir><string name="z" value="weapon"/><string name="_hash" value="d7ad609f4011c05c650f13d91310f0b6fc6ba356ea5ac4f035286238d1bf7d2e"/></canvas><canvas name="effect" width="1" height="1"><vector name="origin" x="106" y="45"/><imgdir name="map"><vector name="navel" x="0" y="0"/></imgdir><string name="z" value="characterEnd"/><string name="_inlink" value="30/swingO1/1/effect"/></canvas></imgdir><imgdir name="2"><canvas name="weapon" width="76" height="67"><vector name="origin" x="78" y="60"/><imgdir name="map"><vector name="navel" x="0" y="0"/></imgdir><string name="z" value="weapon"/><string name="_hash" value="2f7726e79028311b0567956b3094948a2c9f36d7c60efb8f29b380e65bff8e34"/></canvas><canvas name="effect" width="113" height="111"><vector name="origin" x="112" y="100"/><imgdir name="map"><vector name="navel" x="0" y="0"/></imgdir><string name="z" value="characterEnd"/><string name="_hash" value="2f760df8d131f3120f89744c4bd5d30a8959032e3e551c134155dba0e915f7bc"/></canvas></imgdir></imgdir><imgdir name="stabT1"><imgdir name="0"><canvas name="weapon" width="30" height="26"><vector name="origin" x="-8" y="11"/><imgdir name="map"><vector name="navel" x="0" y="0"/></imgdir><string name="z" value="weaponOverBody"/><string name="_hash" value="bf4331e9904472566dd88ef5fe83b0b10a61f6893ff337a984500926e324fc1b"/></canvas><canvas name="effect" width="1" height="1"><vector name="origin" x="53" y="-4"/><imgdir name="map"><vector name="navel" x="0" y="0"/></imgdir><string name="z" value="characterEnd"/><string name="_inlink" value="30/swingO1/0/effect"/></canvas></imgdir><imgdir name="1"><canvas name="weapon" width="102" height="51"><vector name="origin" x="69" y="10"/><imgdir name="map"><vector name="navel" x="0" y="0"/></imgdir><string name="z" value="weaponOverBody"/><string name="_hash" value="caea659bbad8108a2931b4a9e9a9b187ffa0d652289d95dfc7c283f24f87e075"/></canvas><canvas name="effect" width="1" height="1"><vector name="origin" x="75" y="3"/><imgdir name="map"><vector name="navel" x="0" y="0"/></imgdir><string name="z" value="characterEnd"/><string name="_inlink" value="30/swingO1/1/effect"/></canvas></imgdir><imgdir name="2"><canvas name="weapon" width="124" height="80"><vector name="origin" x="108" y="65"/><imgdir name="map"><vector name="navel" x="0" y="0"/></imgdir><string name="z" value="weaponOverBody"/><string name="_hash" value="3ead25c50c2c3460d2ffc8522cf4cc9a2c1775a54d451a779905c833a7fee1ad"/></canvas><canvas name="effect" width="195" height="82"><vector name="origin" x="114" y="75"/><imgdir name="map"><vector name="navel" x="0" y="0"/></imgdir><string name="z" value="characterEnd"/><string name="_hash" value="e85556535ec903ba87ca0ca2fb298e9ee59e4a80879ba240b74e92ce31a73107"/></canvas></imgdir></imgdir><imgdir name="stabT2"><imgdir name="0"><canvas name="weapon" width="28" height="26"><vector name="origin" x="-2" y="11"/><imgdir name="map"><vector name="navel" x="0" y="0"/></imgdir><string name="z" value="weaponOverBody"/><string name="_hash" value="a7591d286abf880e9bbd473106d46621522db40ec2a0f828d02e97abc1553498"/></canvas><canvas name="effect" width="1" height="1"><vector name="origin" x="55" y="-1"/><imgdir name="map"><vector name="navel" x="0" y="0"/></imgdir><string name="z" value="characterEnd"/><string name="_inlink" value="30/swingO1/0/effect"/></canvas></imgdir><imgdir name="1"><canvas name="weapon" width="87" height="59"><vector name="origin" x="59" y="12"/><imgdir name="map"><vector name="navel" x="0" y="0"/></imgdir><string name="z" value="weaponOverBody"/><string name="_hash" value="c7a6bea36317d42c1a2352e23e9ec8f54ea009021d0eef13b2833f598103369c"/></canvas><canvas name="effect" width="80" height="98"><vector name="origin" x="65" y="42"/><imgdir name="map"><vector name="navel" x="0" y="0"/></imgdir><string name="z" value="characterEnd"/><string name="_hash" value="3e683ec73516e8bf9a54682ac6049f32ab93c97c4ef14c6e9e58e090bd865ebe"/></canvas></imgdir><imgdir name="2"><canvas name="weapon" width="118" height="81"><vector name="origin" x="97" y="56"/><imgdir name="map"><vector name="navel" x="0" y="0"/></imgdir><string name="z" value="weaponOverBody"/><string name="_hash" value="585abccda93aa80f9d425530dacc0425c2cc08c846be91457d0b0ad3c89e53a6"/></canvas><canvas name="effect" width="185" height="181"><vector name="origin" x="130" y="95"/><imgdir name="map"><vector name="navel" x="0" y="0"/></imgdir><string name="z" value="characterEnd"/><string name="_hash" value="82048027fb793e0ed1c6f66c490980887ba8a66dbc43ce4f173b29a55360279c"/></canvas></imgdir></imgdir><imgdir name="stabTF"><imgdir name="0"><uol name="weapon" value="../../swingPF/0/weapon"/><uol name="effect" value="../../swingPF/0/effect"/></imgdir><imgdir name="1"><uol name="weapon" value="../../swingPF/1/weapon"/><uol name="effect" value="../../swingPF/1/effect"/></imgdir><imgdir name="2"><canvas name="weapon" width="62" height="48"><vector name="origin" x="-12" y="20"/><imgdir name="map"><vector name="navel" x="0" y="0"/></imgdir><string name="z" value="weaponOverBody"/><string name="_hash" value="930750a3bd28494061caea1e476cc756cd799b9822b01a6f6b6b88a2b3f5c9b7"/></canvas><canvas name="effect" width="165" height="126"><vector name="origin" x="78" y="90"/><imgdir name="map"><vector name="navel" x="0" y="0"/></imgdir><string name="z" value="characterEnd"/><string name="_hash" value="266864637198e99694c8bfea9d469720e7b44d5987c0ba4c988a94bdb049b646"/></canvas></imgdir><imgdir name="3"><uol name="weapon" value="../../stabT1/2/weapon"/><uol name="effect" value="../../stabT1/2/effect"/></imgdir></imgdir><imgdir name="shoot1"><imgdir name="0"><canvas name="weapon" width="86" height="94"><vector name="origin" x="75" y="77"/><imgdir name="map"><vector name="navel" x="0" y="0"/></imgdir><string name="z" value="weaponBelowArm"/><string name="_hash" value="db2d7a55230941c308812f9a191766d0c176fd2943608da7c1d265b0a9b8c64e"/></canvas><canvas name="effect" width="159" height="52"><vector name="origin" x="81" y="32"/><imgdir name="map"><vector name="navel" x="0" y="0"/></imgdir><string name="z" value="characterEnd"/><string name="_hash" value="67e9a76ba104801af435d11631910062ac8cde6bcbfb01275d464675ee7c631a"/></canvas></imgdir><imgdir name="1"><canvas name="weapon" width="79" height="95"><vector name="origin" x="71" y="83"/><imgdir name="map"><vector name="navel" x="0" y="0"/></imgdir><string name="z" value="weaponBelowArm"/><string name="_hash" value="74d7499d3249649b3d47a25fcfc0610e311b85e205bf16c0e048a8c92b8ff997"/></canvas><canvas name="effect" width="177" height="158"><vector name="origin" x="88" y="86"/><imgdir name="map"><vector name="navel" x="0" y="0"/></imgdir><string name="z" value="characterEnd"/><string name="_hash" value="f69a3e42a9c49290cca953290774a2889a5590306025eac80219b173f5ff8097"/></canvas></imgdir><imgdir name="2"><canvas name="weapon" width="86" height="93"><vector name="origin" x="75" y="77"/><imgdir name="map"><vector name="navel" x="0" y="0"/></imgdir><string name="z" value="weaponBelowArm"/><string name="_hash" value="20ef6c828d14010ba9832f426bdf1a0eeacdf9414f27d256d402e2f141d1172e"/></canvas><canvas name="effect" width="153" height="138"><vector name="origin" x="71" y="77"/><imgdir name="map"><vector name="navel" x="0" y="0"/></imgdir><string name="z" value="characterEnd"/><string name="_hash" value="1a41ea6daaa7452cbb07d3a2d4b8776dbd86644cdccc80f36bc71901925464d1"/></canvas></imgdir></imgdir><imgdir name="shoot2"><imgdir name="0"><canvas name="weapon" width="84" height="42"><vector name="origin" x="72" y="23"/><imgdir name="map"><vector name="navel" x="0" y="0"/></imgdir><string name="z" value="weapon"/><string name="_hash" value="79e729ac7c09d6cbb200e20b07a26cff47362ac9db48fde7cada3dea7c7a3fa9"/></canvas><canvas name="effect" width="151" height="29"><vector name="origin" x="70" y="15"/><imgdir name="map"><vector name="navel" x="0" y="0"/></imgdir><string name="z" value="characterEnd"/><string name="_hash" value="13ec01d373e1ab436af0c235968fcab101a0bfe783b5b51c809e7f731a8d0354"/></canvas></imgdir><imgdir name="1"><canvas name="weapon" width="70" height="45"><vector name="origin" x="72" y="33"/><imgdir name="map"><vector name="navel" x="0" y="0"/></imgdir><string name="z" value="weapon"/><string name="_hash" value="c613a33623f77072c198acf58adacffb2496daeabb3e91e2f37f83999f5955ef"/></canvas><canvas name="effect" width="161" height="57"><vector name="origin" x="84" y="43"/><imgdir name="map"><vector name="navel" x="0" y="0"/></imgdir><string name="z" value="characterEnd"/><string name="_hash" value="ecc7f127c070a59de15687dd03fa4222f002c8ad68a1e442db019f9366983074"/></canvas></imgdir><imgdir name="2"><canvas name="weapon" width="105" height="65"><vector name="origin" x="96" y="52"/><imgdir name="map"><vector name="navel" x="0" y="0"/></imgdir><string name="z" value="weapon"/><string name="_hash" value="1d25cf7e2df402d330db8f50b3b65ee809d6e95bc574e493627385fb41b3f96d"/></canvas><canvas name="effect" width="197" height="158"><vector name="origin" x="105" y="87"/><imgdir name="map"><vector name="navel" x="0" y="0"/></imgdir><string name="z" value="characterEnd"/><string name="_hash" value="d896ac9f0dd5adff0faf596ade152b1d67a315f62346a80c54437b09c1a329b2"/></canvas></imgdir><imgdir name="3"><canvas name="weapon" width="84" height="52"><vector name="origin" x="72" y="33"/><imgdir name="map"><vector name="navel" x="0" y="0"/></imgdir><string name="z" value="weapon"/><string name="_hash" value="181d1a8200626d979b26854ce93f5848267ebbb9807feb421b66d21396a19d52"/></canvas><canvas name="effect" width="1" height="1"><vector name="origin" x="68" y="78"/><imgdir name="map"><vector name="navel" x="0" y="0"/></imgdir><string name="z" value="characterEnd"/><string name="_inlink" value="30/shoot1/2/effect"/></canvas></imgdir><imgdir name="4"><canvas name="weapon" width="88" height="42"><vector name="origin" x="72" y="23"/><imgdir name="map"><vector name="navel" x="0" y="0"/></imgdir><string name="z" value="weapon"/><string name="_hash" value="0fa663db035df7c6ddb449cd89902ec24eecbe3e29d4852dc2bb01c71244fa9a"/></canvas><canvas name="effect" width="153" height="138"><vector name="origin" x="68" y="78"/><imgdir name="map"><vector name="navel" x="0" y="0"/></imgdir><string name="z" value="characterEnd"/><string name="_hash" value="69f8d2d13a28c7dd770dff65e0ef25801bd0366a54b26afb87b83f25b1a59f8c"/></canvas></imgdir></imgdir><imgdir name="shootF"><imgdir name="0"><canvas name="weapon" width="39" height="126"><vector name="origin" x="23" y="115"/><imgdir name="map"><vector name="navel" x="0" y="0"/></imgdir><string name="z" value="weaponBelowArm"/><string name="_hash" value="9987863ea66fb85161ec6b0079c54dd5ea2897922178d0bcebff0ed87998ce38"/></canvas><canvas name="effect" width="58" height="194"><vector name="origin" x="29" y="125"/><imgdir name="map"><vector name="navel" x="0" y="0"/></imgdir><string name="z" value="characterEnd"/><string name="_hash" value="545623de72ad375cd680647b2fa7f98919a27ff0b09fc01dfc24d463101d10ea"/></canvas></imgdir><imgdir name="1"><canvas name="weapon" width="46" height="136"><vector name="origin" x="23" y="121"/><imgdir name="map"><vector name="navel" x="0" y="0"/></imgdir><string name="z" value="weaponBelowArm"/><string name="_hash" value="d183c724289b13fc910ebb1e2e1e5940aa9ad339146c479a529914d18f4bd78c"/></canvas><canvas name="effect" width="1" height="1"><vector name="origin" x="86" y="87"/><imgdir name="map"><vector name="navel" x="0" y="0"/></imgdir><string name="z" value="characterEnd"/><string name="_inlink" value="30/shoot1/1/effect"/></canvas></imgdir><imgdir name="2"><uol name="weapon" value="../1/weapon"/><uol name="effect" value="../1/effect"/></imgdir></imgdir><imgdir name="proneStab"><imgdir name="0"><canvas name="weapon" width="104" height="34"><vector name="origin" x="94" y="25"/><imgdir name="map"><vector name="navel" x="0" y="0"/></imgdir><string name="z" value="weaponBelowArm"/><string name="_hash" value="391cd3c72211ce0b8d16484773f60a5e5839ac6ce8703e9764075527301c738a"/></canvas></imgdir><imgdir name="1"><canvas name="weapon" width="90" height="67"><vector name="origin" x="94" y="60"/><imgdir name="map"><vector name="navel" x="0" y="0"/></imgdir><string name="z" value="weaponBelowArm"/><string name="_hash" value="cb628b1a7a5294bbf80f04414d6840429b4cb6804b4478d9a06166be7a889cc9"/></canvas><canvas name="effect" width="1" height="1"><vector name="origin" x="129" y="101"/><imgdir name="map"><vector name="navel" x="0" y="0"/></imgdir><string name="z" value="characterEnd"/><string name="_inlink" value="30/stabOF/2/effect"/></canvas></imgdir></imgdir><imgdir name="prone"><imgdir name="0"><uol name="weapon" value="../../proneStab/0/weapon"/></imgdir></imgdir><imgdir name="heal"><imgdir name="0"><uol name="weapon" value="../../alert/1/weapon"/></imgdir><imgdir name="1"><uol name="weapon" value="../../swingO2/1/weapon"/><uol name="effect" value="../../swingO2/1/effect"/></imgdir><imgdir name="2"><uol name="weapon" value="../../swingO2/0/weapon"/><uol name="effect" value="../../swingO2/0/effect"/></imgdir></imgdir><imgdir name="fly"><imgdir name="0"><canvas name="weapon" width="76" height="51"><vector name="origin" x="13" y="35"/><imgdir name="map"><vector name="navel" x="0" y="0"/></imgdir><string name="z" value="weaponOverArm"/><string name="_hash" value="e2b59bd0ec0a9d8286aac878b47d8c9582cb9fde8816ad201b5cd0328f5f6b36"/></canvas><canvas name="effect" width="30" height="30"><vector name="origin" x="-31" y="22"/><imgdir name="map"><vector name="navel" x="0" y="0"/></imgdir><string name="z" value="characterEnd"/><string name="_hash" value="56127d6b3762be512c26bfb1eab07e3c78a19f8f37af27f35cdf9418c95c9627"/></canvas></imgdir><imgdir name="1"><uol name="weapon" value="../0/weapon"/><uol name="effect" value="../0/effect"/></imgdir></imgdir><imgdir name="jump"><imgdir name="0"><canvas name="weapon" width="80" height="59"><vector name="origin" x="64" y="44"/><imgdir name="map"><vector name="navel" x="0" y="0"/></imgdir><string name="z" value="weaponOverArm"/><string name="_hash" value="89127a5c842bed74a5086b6c5edb7b87a48339fcefdb81e97f655b53ad874c7a"/></canvas><canvas name="effect" width="157" height="125"><vector name="origin" x="81" y="68"/><imgdir name="map"><vector name="navel" x="0" y="0"/></imgdir><string name="z" value="characterEnd"/><string name="_hash" value="64ffa596611e62eb25d9135ddf55a6b1e599ae9bc208387f74ad0383394e85f2"/></canvas></imgdir></imgdir><imgdir name="sit"><imgdir name="0"><canvas name="weapon" width="78" height="85"><vector name="origin" x="42" y="64"/><imgdir name="map"><vector name="navel" x="0" y="0"/></imgdir><string name="z" value="weaponOverGlove"/><string name="_hash" value="0ae44c9243fede456e10ff6b50fc51c8c8b459a6acab0b02821d88d108d6d71c"/></canvas></imgdir></imgdir><imgdir name="ladder"><imgdir name="0"><canvas name="weapon" width="39" height="34"><vector name="origin" x="-17" y="15"/><imgdir name="map"><vector name="navel" x="0" y="0"/></imgdir><string name="z" value="backWeaponOverShield"/><string name="_hash" value="4f41f62be3da6e27e85d1f9f9851eb2a32d007d8167207901123672d599b44be"/></canvas></imgdir><imgdir name="1"><canvas name="weapon" width="35" height="35"><vector name="origin" x="-21" y="16"/><imgdir name="map"><vector name="navel" x="0" y="0"/></imgdir><string name="z" value="backWeaponOverShield"/><string name="_hash" value="0db56e469bbc5c4d347b2290c1aa90ac56bfb7396533eb9c739047891749ffff"/></canvas></imgdir></imgdir><imgdir name="rope"><imgdir name="0"><canvas name="weapon" width="39" height="34"><vector name="origin" x="-17" y="13"/><imgdir name="map"><vector name="navel" x="0" y="0"/></imgdir><string name="z" value="backWeaponOverShield"/><string name="_hash" value="9110d2dd509e4d8de2b23e197fb0e64e3322db61e980f046170ebdefab1939b5"/></canvas></imgdir><imgdir name="1"><canvas name="weapon" width="35" height="39"><vector name="origin" x="-22" y="19"/><imgdir name="map"><vector name="navel" x="0" y="0"/></imgdir><string name="z" value="backWeaponOverShield"/><string name="_hash" value="87cf2f2575d0d329146a2cf82bfe9913758af6d2c67f1e0ab1b97af917a0bd49"/></canvas></imgdir></imgdir></imgdir><imgdir name="49"><uol name="sit" value="../30/sit"/><uol name="ladder" value="../30/ladder"/><uol name="rope" value="../30/rope"/><imgdir name="walk1"><imgdir name="0"><canvas name="weapon" width="63" height="48"><vector name="origin" x="61" y="22"/><imgdir name="map"><vector name="navel" x="0" y="0"/></imgdir><string name="z" value="weapon"/><string name="_hash" value="3f71ac3c369ec64749800fd11bcfb3eb156f3f6bcb645fc9efa447c19a40d8f8"/></canvas></imgdir><imgdir name="1"><canvas name="weapon" width="71" height="48"><vector name="origin" x="64" y="21"/><imgdir name="map"><vector name="navel" x="0" y="0"/></imgdir><string name="z" value="weapon"/><string name="_hash" value="ffdb857a44d82c83e986533c90a2c0bf27d1bdd131ea5db575c0033812a845d5"/></canvas></imgdir><imgdir name="2"><canvas name="weapon" width="74" height="48"><vector name="origin" x="72" y="22"/><imgdir name="map"><vector name="navel" x="0" y="0"/></imgdir><string name="z" value="weapon"/><string name="_hash" value="f2bbf57834c4ac9a6afcb0304d300b1185d1e4f8abfda058c40baf2c3821c3b7"/></canvas></imgdir><imgdir name="3"><canvas name="weapon" width="70" height="43"><vector name="origin" x="71" y="23"/><imgdir name="map"><vector name="navel" x="0" y="0"/></imgdir><string name="z" value="weapon"/><string name="_hash" value="df456bf6b4dc855d3e6b0ab1d897c0bbcff2963a8cb1fc6197967510474c7cf2"/></canvas></imgdir></imgdir><imgdir name="stand1"><imgdir name="0"><canvas name="weapon" width="87" height="42"><vector name="origin" x="59" y="21"/><imgdir name="map"><vector name="navel" x="0" y="0"/></imgdir><string name="z" value="weapon"/><string name="_hash" value="d4efb8b7bf5acb1beb0b2c01dfa47a84cd7063bc1e001735ed46ead61c226fd4"/></canvas></imgdir><imgdir name="1"><canvas name="weapon" width="88" height="42"><vector name="origin" x="60" y="23"/><imgdir name="map"><vector name="navel" x="0" y="0"/></imgdir><string name="z" value="weapon"/><string name="_hash" value="2f3f6bdfca25658eb8f623d4eca4d2ae6e6b05292684aeb9c48f109c3f605767"/></canvas></imgdir><imgdir name="2"><canvas name="weapon" width="89" height="40"><vector name="origin" x="61" y="23"/><imgdir name="map"><vector name="navel" x="0" y="0"/></imgdir><string name="z" value="weapon"/><string name="_hash" value="4f9cedb65cd7b7ebe4cdaebedf1430431366e680a61e7a0d4f075bd07b3c6a6d"/></canvas></imgdir></imgdir><imgdir name="alert"><imgdir name="0"><canvas name="weapon" width="84" height="42"><vector name="origin" x="72" y="24"/><imgdir name="map"><vector name="navel" x="0" y="0"/></imgdir><string name="z" value="weaponOverHand"/><string name="_hash" value="19e4d5188ca92b51cce8a0670ad92eb238b437a2cf4c09f98dc77a0b92bb6c51"/></canvas></imgdir><imgdir name="1"><canvas name="weapon" width="84" height="44"><vector name="origin" x="72" y="24"/><imgdir name="map"><vector name="navel" x="0" y="0"/></imgdir><string name="z" value="weaponOverHand"/><string name="_hash" value="f2302dbcfcb2b9db0ff469d03605454f81f17316d7765a7a152e6962b9513f21"/></canvas></imgdir><imgdir name="2"><canvas name="weapon" width="84" height="46"><vector name="origin" x="72" y="24"/><imgdir name="map"><vector name="navel" x="0" y="0"/></imgdir><string name="z" value="weaponOverHand"/><string name="_hash" value="84f1eca1ce52b4e460a6304959c0ec2c6782d834b1bce336cba27eee727d47e0"/></canvas></imgdir></imgdir><imgdir name="swingO3"><imgdir name="0"><canvas name="weapon" width="29" height="32"><vector name="origin" x="37" y="18"/><imgdir name="map"><vector name="navel" x="0" y="0"/><vector name="muzzle" x="-35" y="-11"/></imgdir><string name="z" value="weapon"/><string name="_hash" value="83799f3d576690a73f0a387d3e0848c14c4b049f01ee1b83ba197fcca3cce61f"/></canvas><canvas name="effect" width="1" height="1"><vector name="origin" x="68" y="51"/><imgdir name="map"><vector name="navel" x="0" y="0"/></imgdir><string name="z" value="characterEnd"/><string name="_inlink" value="30/swingO3/0/effect"/></canvas></imgdir><imgdir name="1"><canvas name="weapon" width="51" height="113"><vector name="origin" x="16" y="102"/><imgdir name="map"><vector name="navel" x="0" y="0"/><vector name="muzzle" x="-4" y="-16"/></imgdir><string name="z" value="weaponBelowBody"/><string name="_hash" value="e6ad2695e8461eb8b36a80f89ee130aa728261d0e9f42d877584c255252b5d10"/></canvas><canvas name="effect" width="114" height="108"><vector name="origin" x="67" y="110"/><imgdir name="map"><vector name="navel" x="0" y="0"/></imgdir><string name="z" value="characterEnd"/><string name="_hash" value="c2ed1f71f8471cae30db6409c36ab48545475b96c0b0fe28ecaab106e8f785d9"/></canvas></imgdir><imgdir name="2"><canvas name="weapon" width="101" height="99"><vector name="origin" x="16" y="90"/><imgdir name="map"><vector name="navel" x="0" y="0"/><vector name="muzzle" x="11" y="-4"/></imgdir><string name="z" value="weaponBelowBody"/><string name="_hash" value="ff16d6c4c83b77c3098110cafa5baa2a66ab250c446c6ae693fdf0d276956174"/></canvas><canvas name="effect" width="1" height="1"><vector name="origin" x="104" y="118"/><imgdir name="map"><vector name="navel" x="0" y="0"/></imgdir><string name="z" value="characterEnd"/><string name="_inlink" value="30/swingO1/2/effect"/></canvas></imgdir></imgdir><imgdir name="swingOF"><imgdir name="3"><canvas name="weapon" width="116" height="73"><vector name="origin" x="27" y="0"/><imgdir name="map"><vector name="navel" x="0" y="0"/><vector name="muzzle" x="-28" y="14"/></imgdir><string name="z" value="weapon"/><string name="_hash" value="14fb155f0651f02f7fc9986ffc32a7e75f7ae0c08533e1f4a377a9848f81446b"/></canvas><canvas name="effect" width="1" height="1"><vector name="origin" x="102" y="90"/><imgdir name="map"><vector name="navel" x="0" y="0"/></imgdir><string name="z" value="characterEnd"/><string name="_inlink" value="30/swingOF/3/effect"/></canvas></imgdir></imgdir><imgdir name="swingT1"><imgdir name="0"><canvas name="weapon" width="29" height="32"><vector name="origin" x="8" y="34"/><imgdir name="map"><vector name="navel" x="0" y="0"/><vector name="muzzle" x="33" y="-30"/></imgdir><string name="z" value="mailArmOverHairBelowWeapon"/><string name="_hash" value="c8862d0d85a614b1e3cf8970bc15a6862862eff0b3e4dd873563de189b99d702"/></canvas><canvas name="effect" width="1" height="1"><vector name="origin" x="-53" y="58"/><imgdir name="map"><vector name="navel" x="0" y="0"/></imgdir><string name="z" value="characterEnd"/><string name="_inlink" value="30/swingT1/0/effect"/></canvas></imgdir><imgdir name="1"><canvas name="weapon" width="39" height="116"><vector name="origin" x="29" y="112"/><imgdir name="map"><vector name="navel" x="0" y="0"/><vector name="muzzle" x="-26" y="-23"/></imgdir><string name="z" value="weaponOverGlove"/><string name="_hash" value="b11f9495a874822d98a1b8e34307822a9164b02f9235a74b51d35819d2abb3d9"/></canvas><canvas name="effect" width="1" height="1"><vector name="origin" x="36" y="121"/><imgdir name="map"><vector name="navel" x="0" y="0"/></imgdir><string name="z" value="characterEnd"/><string name="_inlink" value="30/swingO1/1/effect"/></canvas></imgdir><imgdir name="2"><canvas name="weapon" width="81" height="78"><vector name="origin" x="79" y="-2"/><imgdir name="map"><vector name="navel" x="0" y="0"/><vector name="muzzle" x="-29" y="15"/></imgdir><string name="z" value="weapon"/><string name="_hash" value="16092d2689c04c27dc021f7ed06f588235b2aa01db0ab6789cea3c97b1dda19f"/></canvas><canvas name="effect" width="1" height="1"><vector name="origin" x="110" y="114"/><imgdir name="map"><vector name="navel" x="0" y="0"/></imgdir><string name="z" value="characterEnd"/><string name="_inlink" value="30/swingT1/2/effect"/></canvas></imgdir></imgdir><imgdir name="swingT2"><imgdir name="0"><canvas name="weapon" width="1" height="1"><vector name="origin" x="10" y="30"/><imgdir name="map"><vector name="navel" x="0" y="0"/><vector name="muzzle" x="11" y="-31"/></imgdir><string name="z" value="weapon"/><string name="_inlink" value="30/swingT2/0/weapon"/></canvas><canvas name="effect" width="1" height="1"><vector name="origin" x="-12" y="76"/><imgdir name="map"><vector name="navel" x="0" y="0"/></imgdir><string name="z" value="characterEnd"/><string name="_inlink" value="30/swingT2/0/effect"/></canvas></imgdir><imgdir name="1"><canvas name="weapon" width="71" height="90"><vector name="origin" x="74" y="77"/><imgdir name="map"><vector name="navel" x="0" y="0"/><vector name="muzzle" x="-25" y="-22"/></imgdir><string name="z" value="weapon"/><string name="_hash" value="1e5ecc19c47c652f1fd88dfb04cab306df60439652a6e5ca02e84b8d8b7401c1"/></canvas><canvas name="effect" width="1" height="1"><vector name="origin" x="81" y="110"/><imgdir name="map"><vector name="navel" x="0" y="0"/></imgdir><string name="z" value="characterEnd"/><string name="_inlink" value="30/swingT2/1/effect"/></canvas></imgdir><imgdir name="2"><canvas name="weapon" width="95" height="82"><vector name="origin" x="71" y="2"/><imgdir name="map"><vector name="navel" x="0" y="0"/><vector name="muzzle" x="-8" y="11"/></imgdir><string name="z" value="weaponOverBody"/><string name="_hash" value="041eba8f234ea7fb56ece505c42e9ae8107ccf3dd10a9f20613ef000fae715ad"/></canvas><canvas name="effect" width="1" height="1"><vector name="origin" x="107" y="109"/><imgdir name="map"><vector name="navel" x="0" y="0"/></imgdir><string name="z" value="characterEnd"/><string name="_inlink" value="30/swingT2/2/effect"/></canvas></imgdir></imgdir><imgdir name="swingT3"><imgdir name="0"><canvas name="weapon" width="29" height="26"><vector name="origin" x="8" y="4"/><imgdir name="map"><vector name="navel" x="0" y="0"/><vector name="muzzle" x="23" y="2"/></imgdir><string name="z" value="weapon"/><string name="_hash" value="cdf7c8116d44a2c9d678cf6955fcb09c58ffc75075fddc15d5c4fa1ae7f3da2a"/></canvas><canvas name="effect" width="1" height="1"><vector name="origin" x="-44" y="12"/><imgdir name="map"><vector name="navel" x="0" y="0"/></imgdir><string name="z" value="characterEnd"/><string name="_inlink" value="30/swingT3/0/effect"/></canvas></imgdir><imgdir name="1"><canvas name="weapon" width="42" height="92"><vector name="origin" x="23" y="4"/><imgdir name="map"><vector name="navel" x="0" y="0"/><vector name="muzzle" x="17" y="8"/></imgdir><string name="z" value="weaponOverBody"/><string name="_hash" value="f0c6b3359fbece9213bb8e86fa2ccd23ad024e80051e5a604ffbbb7bfa3f649a"/></canvas><canvas name="effect" width="1" height="1"><vector name="origin" x="30" y="11"/><imgdir name="map"><vector name="navel" x="0" y="0"/></imgdir><string name="z" value="characterEnd"/><string name="_inlink" value="30/swingT3/1/effect"/></canvas></imgdir><imgdir name="2"><canvas name="weapon" width="72" height="90"><vector name="origin" x="73" y="29"/><imgdir name="map"><vector name="navel" x="0" y="0"/><vector name="muzzle" x="3" y="-28"/></imgdir><string name="z" value="weapon"/><string name="_hash" value="eb882f8b192105d66da4596a12b327da290d46913170f81ea7a0d90ad1a993b3"/></canvas><canvas name="effect" width="186" height="204"><vector name="origin" x="100" y="115"/><imgdir name="map"><vector name="navel" x="0" y="0"/></imgdir><string name="z" value="characterEnd"/><string name="_hash" value="901ed1173938404cab121434eae50845e676237a4363963e9359b56b6c80329a"/></canvas></imgdir></imgdir><imgdir name="stabO1"><imgdir name="0"><canvas name="weapon" width="29" height="25"><vector name="origin" x="33" y="12"/><imgdir name="map"><vector name="navel" x="0" y="0"/><vector name="muzzle" x="-34" y="-5"/></imgdir><string name="z" value="weaponOverArmBelowHead"/><string name="_hash" value="3725fcb63447e93a47d6b514c70acd7e01a1dc9ce507b6079d6d740e95ce2578"/></canvas><canvas name="effect" width="1" height="1"><vector name="origin" x="61" y="21"/><imgdir name="map"><vector name="navel" x="0" y="0"/></imgdir><string name="z" value="characterEnd"/><string name="_inlink" value="30/stabO1/0/effect"/></canvas></imgdir><imgdir name="1"><canvas name="weapon" width="128" height="35"><vector name="origin" x="105" y="23"/><imgdir name="map"><vector name="navel" x="0" y="0"/><vector name="muzzle" x="-13" y="-3"/></imgdir><string name="z" value="weaponBelowBody"/><string name="_hash" value="853f0a67c7d8751b11efad8da4e0967f6b2e3a5893246675ded18bbf99a5ebd2"/></canvas><canvas name="effect" width="1" height="1"><vector name="origin" x="139" y="97"/><imgdir name="map"><vector name="navel" x="0" y="0"/></imgdir><string name="z" value="characterEnd"/><string name="_inlink" value="30/stabO1/1/effect"/></canvas></imgdir></imgdir><imgdir name="stabO2"><imgdir name="0"><canvas name="weapon" width="28" height="26"><vector name="origin" x="33" y="13"/><imgdir name="map"><vector name="navel" x="0" y="0"/><vector name="muzzle" x="-35" y="-7"/></imgdir><string name="z" value="weaponOverArmBelowHead"/><string name="_hash" value="9be7ca0d6e9899a3b1c01c4939bcee08e34e4f11e853ba2ea74379b4957b8e15"/></canvas><canvas name="effect" width="1" height="1"><vector name="origin" x="58" y="10"/><imgdir name="map"><vector name="navel" x="0" y="0"/></imgdir><string name="z" value="characterEnd"/><string name="_inlink" value="30/swingO1/0/effect"/></canvas></imgdir><imgdir name="1"><canvas name="weapon" width="135" height="83"><vector name="origin" x="111" y="70"/><imgdir name="map"><vector name="navel" x="0" y="0"/><vector name="muzzle" x="-8" y="-2"/></imgdir><string name="z" value="weaponBelowBody"/><string name="_hash" value="f98882be38212d009c59a52e3a7e9d0cfc67b860e9715d2bc113612dd9e0a927"/></canvas><canvas name="effect" width="1" height="1"><vector name="origin" x="119" y="85"/><imgdir name="map"><vector name="navel" x="0" y="0"/></imgdir><string name="z" value="characterEnd"/><string name="_inlink" value="30/stabO2/1/effect"/></canvas></imgdir></imgdir><imgdir name="stabT2"><imgdir name="1"><canvas name="weapon" width="56" height="52"><vector name="origin" x="58" y="6"/><imgdir name="map"><vector name="navel" x="0" y="0"/><vector name="muzzle" x="-29" y="6"/></imgdir><string name="z" value="weapon"/><string name="_hash" value="e3e90c8e361cc22cda4940f3f3d472d8de20eb119d1ca4638dee6a39ab3a8c6b"/></canvas><canvas name="effect" width="1" height="1"><vector name="origin" x="65" y="-4"/><imgdir name="map"><vector name="navel" x="0" y="0"/></imgdir><string name="z" value="characterEnd"/><string name="_inlink" value="30/swingO1/1/effect"/></canvas></imgdir></imgdir><imgdir name="shoot2"><imgdir name="0"><canvas name="weapon" width="67" height="43"><vector name="origin" x="71" y="24"/><imgdir name="map"><vector name="navel" x="0" y="0"/><vector name="muzzle" x="-17" y="-17"/></imgdir><string name="z" value="mailArmOverHairBelowWeapon"/><string name="_hash" value="8acaa648396bad389a5cc129a2bff2ce645632d9c2d7276c8609bb1c1d9ec8a8"/></canvas><canvas name="effect" width="1" height="1"><vector name="origin" x="70" y="15"/><imgdir name="map"><vector name="navel" x="0" y="0"/></imgdir><string name="z" value="characterEnd"/><string name="_inlink" value="30/shoot2/0/effect"/></canvas></imgdir></imgdir><imgdir name="swingP1"><imgdir name="0"><canvas name="weapon" width="29" height="32"><vector name="origin" x="15" y="37"/><imgdir name="map"><vector name="navel" x="0" y="0"/><vector name="muzzle" x="11" y="-37"/></imgdir><string name="z" value="mailArmOverHairBelowWeapon"/><string name="_hash" value="926a3d58ecd0400b07aa4d5966ac953dea495c2a44c1dbfda1720c0e5d835e17"/></canvas><canvas name="effect" width="1" height="1"><vector name="origin" x="-50" y="66"/><imgdir name="map"><vector name="navel" x="0" y="0"/></imgdir><string name="z" value="characterEnd"/><string name="_inlink" value="30/swingO1/0/effect"/></canvas></imgdir><imgdir name="1"><canvas name="weapon" width="39" height="120"><vector name="origin" x="31" y="103"/><imgdir name="map"><vector name="navel" x="0" y="0"/><vector name="muzzle" x="-31" y="-17"/></imgdir><string name="z" value="weaponOverGlove"/><string name="_hash" value="ddcedf017492e459e40527436b2263c54eb3481f4a7791711dff40e4366926d6"/></canvas><canvas name="effect" width="1" height="1"><vector name="origin" x="38" y="112"/><imgdir name="map"><vector name="navel" x="0" y="0"/></imgdir><string name="z" value="characterEnd"/><string name="_inlink" value="30/swingO1/1/effect"/></canvas></imgdir><imgdir name="2"><canvas name="weapon" width="82" height="78"><vector name="origin" x="81" y="-1"/><imgdir name="map"><vector name="navel" x="0" y="0"/><vector name="muzzle" x="-31" y="15"/></imgdir><string name="z" value="weapon"/><string name="_hash" value="46c994336093afb17633d715b5944f3383ea93e50b2511f2d82113e350d0ed04"/></canvas><canvas name="effect" width="1" height="1"><vector name="origin" x="112" y="115"/><imgdir name="map"><vector name="navel" x="0" y="0"/></imgdir><string name="z" value="characterEnd"/><string name="_inlink" value="30/swingT1/2/effect"/></canvas></imgdir></imgdir><imgdir name="swingP2"><imgdir name="0"><canvas name="weapon" width="23" height="35"><vector name="origin" x="28" y="26"/><imgdir name="map"><vector name="navel" x="0" y="0"/><vector name="muzzle" x="-7" y="-24"/></imgdir><string name="z" value="weapon"/><string name="_hash" value="cbe761caf7ae3aa6b7174b335d36aec3b69629509e1b37f2798639b8b6d5b17a"/></canvas><canvas name="effect" width="1" height="1"><vector name="origin" x="11" y="74"/><imgdir name="map"><vector name="navel" x="0" y="0"/></imgdir><string name="z" value="characterEnd"/><string name="_inlink" value="30/swingO1/0/effect"/></canvas></imgdir><imgdir name="1"><canvas name="weapon" width="39" height="116"><vector name="origin" x="33" y="95"/><imgdir name="map"><vector name="navel" x="0" y="0"/><vector name="muzzle" x="-11" y="-16"/></imgdir><string name="z" value="weapon"/><string name="_hash" value="bb260e9b38096149485a90af9a9bc521a4c79c6fa7e846bff6eabb5ab3c4d2ac"/></canvas><canvas name="effect" width="1" height="1"><vector name="origin" x="41" y="104"/><imgdir name="map"><vector name="navel" x="0" y="0"/></imgdir><string name="z" value="characterEnd"/><string name="_inlink" value="30/swingO1/1/effect"/></canvas></imgdir><imgdir name="2"><canvas name="weapon" width="96" height="82"><vector name="origin" x="72" y="2"/><imgdir name="map"><vector name="navel" x="0" y="0"/><vector name="muzzle" x="-10" y="11"/></imgdir><string name="z" value="weaponOverBody"/><string name="_hash" value="2eca010ff3438df19d4edf998d0c2e3cfde94826cfcbb04c90e3a86d4aab679d"/></canvas><canvas name="effect" width="1" height="1"><vector name="origin" x="109" y="109"/><imgdir name="map"><vector name="navel" x="0" y="0"/></imgdir><string name="z" value="characterEnd"/><string name="_inlink" value="30/swingT2/2/effect"/></canvas></imgdir></imgdir><imgdir name="swingPF"><imgdir name="3"><canvas name="weapon" width="103" height="71"><vector name="origin" x="99" y="7"/><imgdir name="map"><vector name="navel" x="0" y="0"/><vector name="muzzle" x="-33" y="20"/></imgdir><string name="z" value="weapon"/><string name="_hash" value="830b65f4eb1ae275ff409c85a53503a55ddeac69464dbd0fae61ba36a88afc5f"/></canvas><canvas name="effect" width="1" height="1"><vector name="origin" x="123" y="117"/><imgdir name="map"><vector name="navel" x="0" y="0"/></imgdir><string name="z" value="characterEnd"/><string name="_inlink" value="30/swingTF/3/effect"/></canvas></imgdir></imgdir><imgdir name="proneStab"><imgdir name="0"><canvas name="weapon" width="78" height="34"><vector name="origin" x="93" y="26"/><imgdir name="map"><vector name="navel" x="0" y="0"/><vector name="muzzle" x="-50" y="-2"/></imgdir><string name="z" value="weapon"/><string name="_hash" value="a50ddf8d9145e66b80b4f1c61aaa3b9f4862fc9908c7e11eda1b76d3aa296fc3"/></canvas></imgdir><imgdir name="1"><canvas name="weapon" width="78" height="68"><vector name="origin" x="93" y="61"/><imgdir name="map"><vector name="navel" x="0" y="0"/><vector name="muzzle" x="-51" y="-2"/></imgdir><string name="z" value="weapon"/><string name="_hash" value="4a2b188c832586f5ef5237f562855cb52fce939a48f2c086d86ffe57a78838b0"/></canvas><canvas name="effect" width="1" height="1"><vector name="origin" x="129" y="101"/><imgdir name="map"><vector name="navel" x="0" y="0"/></imgdir><string name="z" value="characterEnd"/><string name="_inlink" value="30/stabOF/2/effect"/></canvas></imgdir></imgdir><imgdir name="prone"><imgdir name="0"><uol name="weapon" value="../../proneStab/0/weapon"/></imgdir></imgdir><imgdir name="fly"><imgdir name="0"><canvas name="weapon" width="81" height="56"><vector name="origin" x="17" y="35"/><imgdir name="map"><vector name="navel" x="0" y="0"/></imgdir><string name="z" value="weaponOverGlove"/><string name="_hash" value="e6d2957ec8577b5d748785063f125ff8d4d0b4879e91fa2a2ce662b971b8a93d"/></canvas><canvas name="effect" width="1" height="1"><vector name="origin" x="-31" y="22"/><imgdir name="map"><vector name="navel" x="0" y="0"/></imgdir><string name="z" value="weaponOverBody"/><string name="_inlink" value="30/fly/0/effect"/></canvas></imgdir><imgdir name="1"><canvas name="weapon" width="77" height="55"><vector name="origin" x="17" y="34"/><imgdir name="map"><vector name="navel" x="0" y="0"/></imgdir><string name="z" value="weaponOverGlove"/><string name="_hash" value="2a54f78c450bd545fd6a3599989eb5cdee18758e45c13c4e7844b4621d506d4a"/></canvas></imgdir></imgdir><imgdir name="jump"><imgdir name="0"><canvas name="weapon" width="69" height="64"><vector name="origin" x="63" y="45"/><imgdir name="map"><vector name="navel" x="0" y="0"/></imgdir><string name="z" value="weaponOverGlove"/><string name="_hash" value="5da5b269af8b0e7d8b0df355146d450ce4464f8832608e2d7c7fbb26b5d25e6b"/></canvas><canvas name="effect" width="1" height="1"><vector name="origin" x="81" y="68"/><imgdir name="map"><vector name="navel" x="0" y="0"/></imgdir><string name="z" value="characterEnd"/><string name="_inlink" value="30/jump/0/effect"/></canvas></imgdir></imgdir></imgdir></imgdir>